arriveAndDepartSignal.v
/*`include"Metastability.v"
`include"counter.v"
*/
/*
// module for arrival, departure, inner port, and outer port
module arriveAndDepartSignal(arriveSignal, departSignal, arriveSwitch,
                             departSwitch, clk, rst);
    output arriveSignal;
    output departSignal;
    input arriveSwitch;
    input departSwitch;
    input pressureUp;
    input pressureDown;
    input clk, rst;

    reg departPS;
    reg departNS;
    reg arrivePS;
    reg arriveNS;

    Metastability arrive(.clk(), .rst(), .press(arriveSwitch), .metaFree(arriveSignal)); // prevent metastability from the signals
    Metastability depart(.clk(), .rst(), .press(departSwitch), .metaFree(departSignal));

    //counter pressureUpCount(.clk(clk), .reset(rst), .counterSeconds(10'b111), .signal(pressureUp)); // interface with counters
    //counter pressureDownCount(.clk(clk), .reset(rst), .counterSeconds(10'b111), .signal(pressureDown));
    //FillandPressurize isPressurized(.Clock, .Reset, .begin_FandP, .InnerClosed, .OuterClosed, .Evacuated, .Pressurized, .FandP(pressureUp));

    assign arriveSignal = arrivePS; // assign the signals to present states
    assign departSignal = departPS;

    always @(*)
        begin
            if (arriveSwitch && FPState == 0) begin // if switch is enabled and pressureUp counter is greater than 0 && pressureDown counter is 0
                arriveNS = 1;
            end
            else if (arrivePS && FPState == 0) begin // if present state is on and pressureUp counter is greater than 0 next
                arriveNS = 1;
            end
            if (departSwitch &&  EvState == 0) begin // if switch is enabled and pressureDown counter is greater than 0 && pressureUp counter is 0
                departNS = 1;
            end
            else if (departPS && EVState == 0) begin // if present state is on and pressureDown counter is greater than o
                departNS = 1;
            end
            else begin // else turn off both signals
                arriveNS = 0;
                departNS = 0;
            end
        end

    always@(posedge clk)
    	if(!rst) begin
    		arrivePS <= 0;
            departPS <= 0;
    	end
    	else begin
            arrivePS <= arriveNS;
            departPS <= departNS;
    	end
endmodule
*/
// module for arrival, departure, inner port, and outer port
module arriveAndDepartSignal(arriveSignal, departSignal, arriveSwitch,
                             departSwitch, clk, rst);
    output arriveSignal;
    output departSignal;
    input arriveSwitch;
    input departSwitch;
    input clk, rst;

    reg departPS;
    reg departNS;
    reg arrivePS;
    reg arriveNS;

    assign arriveSignal = arrivePS; // assign the signals to present states
    assign departSignal = departPS;

    always @(*)
        begin
            if (arriveSwitch && !departSwitch) begin // if switch is enabled and pressureUp counter is greater than 0 && pressureDown counter is 0
                arriveNS = 1;
					 departNS = 0;
            end
            else if (!arriveSwitch && departSwitch) begin // if present state is on and pressureUp counter is greater than 0 next
                arriveNS = 0;
					 departNS = 1;
            end 
				else begin // else turn off both signals
                arriveNS = 0;
                departNS = 0;
            end
        end

    always@(posedge clk)
    	if(!rst) begin
    		arrivePS <= 0;
         departPS <= 0;
    	end
    	else begin
            arrivePS <= arriveNS;
            departPS <= departNS;
    	end
endmodule

arriveAndDepartSignal_tester.v
module arriveAndDepartSignal_tester(clk, rst, arriveSwitch, departSwitch);
	output reg clk, rst, arriveSwitch, departSwitch;
	
	// Set up the clock.
	parameter CLOCK_PERIOD=2;
	initial clk=1;
	always begin
		#(CLOCK_PERIOD/2);
		clk = ~clk;
	end
	
	// Set up the inputs to the design. Each line is a clock cycle.
	initial begin
		departSwitch <= 0; arriveSwitch <= 0;
		@(posedge clk);
		rst <= 1;	
		@(posedge clk);			
		rst <= 0;					
		@(posedge clk);
		rst <= 1;						
		@(posedge clk);
		arriveSwitch <= 1;			
		@(posedge clk);
		departSwitch <= 1;	
		@(posedge clk);
		arriveSwitch <= 0;
		@(posedge clk);
		departSwitch <= 0;
		@(posedge clk);
	end
endmodule

arriveAndDepartSignal_testbench.v
`include "arriveAndDepartSignal.v"
`include "arriveAndDepartSignal_tester.v"

module arriveAndDepartSignal_testbench();

	wire clk, rst, arriveSwitch, departSwitch, arriveSignal, departSignal;
	
	// Calls the arriveAndDepartSignal tester module 
	arriveAndDepartSignal_tester t(.clk(clk), .rst(rst), .arriveSwitch(arriveSwitch),
                             .departSwitch(departSwitch));
	
	// Calls the arriveAndDepartSignal module as the device under test (dut 
	arriveAndDepartSignal dut(.arriveSignal(arriveSignal), .departSignal(departSignal), .arriveSwitch(arriveSwitch),
                             .departSwitch(departSwitch), .clk(clk), .rst(rst));
	
	// Dumps the results of the simulation into a .vcd file for view in GTKWave
	initial begin 
		$dumpfile("arriveAndDepartSignal.vcd");
		$dumpvars(0, arriveAndDepartSignal_testbench);
		#150;
		$finish;
	end 
	
endmodule

arriveAndDepartSignal.vcd
$date
	Sat Apr 23 08:31:38 2016
$end
$version
	Icarus Verilog
$end
$timescale
	1s
$end
$scope module arriveAndDepartSignal_testbench $end
$var wire 1 ! arriveSignal $end
$var wire 1 " arriveSwitch $end
$var wire 1 # clk $end
$var wire 1 $ departSignal $end
$var wire 1 % departSwitch $end
$var wire 1 & rst $end
$scope module t $end
$var reg 1 ' arriveSwitch $end
$var reg 1 ( clk $end
$var reg 1 ) departSwitch $end
$var reg 1 * rst $end
$upscope $end
$scope module dut $end
$var wire 1 ! arriveSignal $end
$var wire 1 " arriveSwitch $end
$var wire 1 # clk $end
$var wire 1 $ departSignal $end
$var wire 1 % departSwitch $end
$var wire 1 & rst $end
$var reg 1 + arriveNS $end
$var reg 1 , arrivePS $end
$var reg 1 - departNS $end
$var reg 1 . departPS $end
$upscope $end
$upscope $end
$enddefinitions $end
#0
$dumpvars
x.
0-
x,
0+
x*
0)
1(
0'
x&
0%
x$
1#
0"
x!
$end
#1
0(
0#
#2
1*
1&
0.
0$
0,
0!
1(
1#
#3
0(
0#
#4
0*
0&
1(
1#
#5
0(
0#
#6
1*
1&
1(
1#
#7
0(
0#
#8
1+
1'
1"
1(
1#
#9
0(
0#
#10
0+
1)
1%
1,
1!
1(
1#
#11
0(
0#
#12
1-
0,
0!
0'
0"
1(
1#
#13
0(
0#
#14
0-
0)
0%
1.
1$
1(
1#
#15
0(
0#
#16
0.
0$
1(
1#
