countdown_Evacuate.v
module countdown_Evacuate(Clock, Reset, countdown, evacuated);
	input Clock, Reset, countdown;
	output reg evacuated;
	
	parameter A = 4'b1000,  B = 4'b0111, C = 4'b0110, D = 4'b0101, E = 4'b0100, F = 4'b0011, G = 4'b0010, H = 4'b0001, I = 4'b0000;
	
	reg [3:0] ps;
	reg [3:0] ns; 
	
	always@(*)
	
		case (ps)
		
			A: begin 
			
				if(countdown) begin
				ns = B;
				evacuated = 0;
				end
				
				else begin
				ns = A;
				evacuated = 0;
				end
				
		
			end 
			
			B: begin 
			ns = C;	
			evacuated = 0;
			end 
			
			C: begin 
			ns = D;
			evacuated = 0;
			end 
			
			D: begin 
			ns = E;
			evacuated = 0;
			end 
			
			E: begin 
			ns = F;
			evacuated = 0;
			end 
			
			F: begin 
			ns = G;
			evacuated = 0;
			end 
			
			G: begin 
			ns = H;
			evacuated = 0;
			end 
			
			H: begin 
			ns = I;
			evacuated = 0;
			end 
			
			I: begin 
			ns = A;
			evacuated = 1;
			end 
		
		endcase
		
	always@(posedge Clock)
		if(!Reset) begin
			ps <= A;
			
		end 
				
		else begin
		
			ps <= ns;
			
		end 
	
endmodule

countdown_Evacuate_tester.v
module countdown_Evacuate_tester(Clock, Reset, countdown);
	output reg Clock, Reset, countdown;
	
	// Set up the clock.
	parameter CLOCK_PERIOD=2;
	initial Clock=1;
	always begin
		#(CLOCK_PERIOD/2);
		Clock = ~Clock;
	end
	
	// Set up the inputs to the design. Each line is a clock cycle.
	initial begin
										@(posedge Clock);
		Reset <= 0;						@(posedge Clock);			
										@(posedge Clock);
		Reset <= 1; countdown <= 1;		@(posedge Clock);
		countdown <= 0;					@(posedge Clock);
										@(posedge Clock);
										@(posedge Clock);
										@(posedge Clock);
										@(posedge Clock);
										@(posedge Clock);
										@(posedge Clock);
										@(posedge Clock);
										@(posedge Clock);
										@(posedge Clock);
										@(posedge Clock);
										@(posedge Clock);
										@(posedge Clock);
										@(posedge Clock);
										@(posedge Clock);
										@(posedge Clock);


	end
endmodule

countdown_Evacuate_testbench.v
`include "countdown_Evacuate.v"
`include "countdown_Evacuate_tester.v"

module countdown_Evacuate_testbench();

	wire Clock, Reset, countdown;
	wire evacuated;
	
	// Calls the 1 bit counter tester module 
	// Notice that the output Clock, Reset, Increase of the tester module are wires Clock, Reset, Increase in this module
	countdown_Evacuate_tester t(.Clock(Clock), .Reset(Reset), .countdown(countdown));
	
	// Calls the 1 bit counter module as the device under test (dut)
	// Notice that the Clock, Reset, and Increase are wired to the input of the 1 bit counter module  
	countdown_Evacuate dut(.Clock(Clock), .Reset(Reset), .countdown(countdown), .evacuated(evacuated));
	
	// Dumps the results of the simulation into a .vcd file for view in GTKWave
	initial begin 
		$dumpfile("countdown_Evacuate.vcd");
		$dumpvars(0, countdown_Evacuate_testbench);
		#150;
		$finish;
	end 
	
endmodule

countdown_Evacuate.vcd
$date
	Thu Apr 21 08:51:01 2016
$end
$version
	Icarus Verilog
$end
$timescale
	1s
$end
$scope module countdown_Evacuate_testbench $end
$var wire 1 ! Clock $end
$var wire 1 " Reset $end
$var wire 1 # countdown $end
$var wire 1 $ evacuated $end
$scope module t $end
$var reg 1 % Clock $end
$var reg 1 & Reset $end
$var reg 1 ' countdown $end
$upscope $end
$scope module dut $end
$var wire 1 ! Clock $end
$var wire 1 " Reset $end
$var wire 1 # countdown $end
$var reg 1 ( evacuated $end
$var reg 4 ) ns [3:0] $end
$var reg 4 * ps [3:0] $end
$upscope $end
$upscope $end
$enddefinitions $end
#0
$dumpvars
bx *
bx )
x(
x'
x&
1%
x$
x#
x"
1!
$end
#1
0%
0!
#2
0&
0"
1%
1!
#3
0%
0!
#4
0(
0$
b1000 )
b1000 *
1%
1!
#5
0%
0!
#6
b111 )
1'
1#
1&
1"
1%
1!
#7
0%
0!
#8
b110 )
b111 *
0'
0#
1%
1!
#9
0%
0!
#10
b101 )
b110 *
1%
1!
#11
0%
0!
#12
b100 )
b101 *
1%
1!
#13
0%
0!
#14
b11 )
b100 *
1%
1!
#15
0%
0!
#16
b10 )
b11 *
1%
1!
#17
0%
0!
#18
b1 )
b10 *
1%
1!
#19
0%
0!
#20
b0 )
b1 *
1%
1!
#21
0%
0!
#22
1(
1$
b1000 )
b0 *
1%
1!
#23
0%
0!
#24
0(
0$
b1000 *
1%
1!
