countdown_FP.v
module countdown_FP(Clock, Reset, countdown, pressurized);
	input Clock, Reset, countdown;
	output reg pressurized;
	
	parameter A = 3'b111, B = 3'b110, C = 3'b101, D = 3'b100, E = 3'b011, F = 3'b010, G = 3'b001, H = 3'b000;
	
	reg [2:0] ps;
	reg [2:0] ns; 
	
	always@(*)
	
		case (ps)
		
			A: begin 
			
				if(countdown) begin
				ns = B;
				pressurized = 0;
				end 
				
				else begin
				ns = A;
				pressurized = 0;
				end
		
			end 
			
			B: begin 
			ns = C;	
			pressurized = 0;
			end 
			
			C: begin 
			ns = D;
			pressurized = 0;
			end 
			
			D: begin 
			ns = E;
			pressurized = 0;
			end 
			
			E: begin 
			ns = F;
			pressurized = 0;
			end 
			
			F: begin 
			ns = G;
			pressurized = 0;
			end 
			
			F: begin 
			ns = G;
			pressurized = 0;
			end 
			
			G: begin 
			ns = H;
			pressurized = 0;
			end 
			
			H: begin 
			ns = A;
			pressurized = 1; 
			end 
		
		endcase
		
	always@(posedge Clock)
		if(!Reset) begin

			ps <= A;
			
		end 
				
		else begin
		
			ps <= ns;
			
		end 
	
endmodule

countdown_FP_tester.v
module countdown_FP_tester(Clock, Reset, countdown);
	output reg Clock, Reset, countdown;
	
	// Set up the clock.
	parameter CLOCK_PERIOD=2;
	initial Clock=1;
	always begin
		#(CLOCK_PERIOD/2);
		Clock = ~Clock;
	end
	
	// Set up the inputs to the design. Each line is a clock cycle.
	initial begin
										@(posedge Clock);
		Reset <= 0;						@(posedge Clock);			
										@(posedge Clock);
		Reset <= 1; countdown <= 1;		@(posedge Clock);
		countdown <= 0;					@(posedge Clock);
										@(posedge Clock);
										@(posedge Clock);
										@(posedge Clock);
										@(posedge Clock);
										@(posedge Clock);
										@(posedge Clock);
										@(posedge Clock);
										@(posedge Clock);
										@(posedge Clock);
										@(posedge Clock);
										@(posedge Clock);
										@(posedge Clock);
										@(posedge Clock);
										@(posedge Clock);
										@(posedge Clock);


	end
endmodule

countdown_FP_testbench.v
`include "countdown_FP.v"
`include "countdown_FP_tester.v"

module countdown_FP_testbench();

	wire Clock, Reset, countdown;
	wire pressurized;
	
	// Calls the 1 bit counter tester module 
	// Notice that the output Clock, Reset, Increase of the tester module are wires Clock, Reset, Increase in this module
	countdown_FP_tester t(.Clock(Clock), .Reset(Reset), .countdown(countdown));
	
	// Calls the 1 bit counter module as the device under test (dut)
	// Notice that the Clock, Reset, and Increase are wired to the input of the 1 bit counter module  
	countdown_FP dut(.Clock(Clock), .Reset(Reset), .countdown(countdown), .pressurized(pressurized));
	
	// Dumps the results of the simulation into a .vcd file for view in GTKWave
	initial begin 
		$dumpfile("countdown_FP.vcd");
		$dumpvars(0, countdown_FP_testbench);
		#150;
		$finish;
	end 
	
endmodule

countdown_FP.vcd
$date
	Thu Apr 21 08:40:42 2016
$end
$version
	Icarus Verilog
$end
$timescale
	1s
$end
$scope module countdown_FP_testbench $end
$var wire 1 ! Clock $end
$var wire 1 " Reset $end
$var wire 1 # countdown $end
$var wire 1 $ pressurized $end
$scope module t $end
$var reg 1 % Clock $end
$var reg 1 & Reset $end
$var reg 1 ' countdown $end
$upscope $end
$scope module dut $end
$var wire 1 ! Clock $end
$var wire 1 " Reset $end
$var wire 1 # countdown $end
$var reg 3 ( ns [2:0] $end
$var reg 1 ) pressurized $end
$var reg 3 * ps [2:0] $end
$upscope $end
$upscope $end
$enddefinitions $end
#0
$dumpvars
bx *
x)
bx (
x'
x&
1%
x$
x#
x"
1!
$end
#1
0%
0!
#2
0&
0"
1%
1!
#3
0%
0!
#4
0)
0$
b111 (
b111 *
1%
1!
#5
0%
0!
#6
b110 (
1'
1#
1&
1"
1%
1!
#7
0%
0!
#8
b101 (
b110 *
0'
0#
1%
1!
#9
0%
0!
#10
b100 (
b101 *
1%
1!
#11
0%
0!
#12
b11 (
b100 *
1%
1!
#13
0%
0!
#14
b10 (
b11 *
1%
1!
#15
0%
0!
#16
b1 (
b10 *
1%
1!
#17
0%
0!
#18
b0 (
b1 *
1%
1!
#19
0%
0!
#20
1)
1$
b111 (
b0 *
1%
1!
#21
0%
0!
#22
0)
0$
b111 *
1%
1!
