Evacuate.v
module Evacuate(Clock, Reset, begin_Evacuation, InnerClosed, OuterClosed, Evacuated, Evacuation);
	input Clock, Reset, begin_Evacuation, InnerClosed, OuterClosed, Evacuated;
	output Evacuation;
	
	parameter A = 0, B = 1;
	
	reg ps;
	reg ns;
	
	always@(*)
	
		case (InnerClosed)
		
			A: begin 
			
				ns = A;
			
			end 
			
			
			B: begin 
			
				if (!Evacuated && begin_Evacuation && OuterClosed) ns = B;
				else ns = A;
				
			end 
		
		endcase
		
	assign Evacuation = (ps); 
		
	always@(posedge Clock)
		if(Reset) begin
		
			ps <= A;
			
		end 
				
		else begin
		
			ps <= ns;
			
		end 
	
endmodule

Evacuate_tester.v
module Evacuate_tester(Clock, Reset, begin_Evacuation, InnerClosed, OuterClosed, Evacuated);
	output reg Clock, Reset, begin_Evacuation, InnerClosed, OuterClosed, Evacuated;
	
	// Set up the clock.
	parameter CLOCK_PERIOD=2;
	initial Clock=1;
	always begin
		#(CLOCK_PERIOD/2);
		Clock = ~Clock;
	end
	
	// Set up the inputs to the design. Each line is a clock cycle.
	initial begin
										@(posedge Clock);
		Reset <= 1;						@(posedge Clock);			
										@(posedge Clock);
		Reset <= 0; OuterClosed <= 0;	@(posedge Clock);
		InnerClosed <= 0;				@(posedge Clock);
		Evacuated <= 0;					@(posedge Clock);
										@(posedge Clock);
		begin_Evacuation <= 1;			@(posedge Clock);
										@(posedge Clock);
										@(posedge Clock);
										@(posedge Clock);
		Evacuated <= 1;					@(posedge Clock);
										@(posedge Clock);
										@(posedge Clock);
										@(posedge Clock);
		begin_Evacuation <= 1;			@(posedge Clock);
										@(posedge Clock);
		InnerClosed <= 1;				@(posedge Clock);
										@(posedge Clock);
										@(posedge Clock);
		OuterClosed <= 1;				@(posedge Clock);
		Evacuated <= 0;					@(posedge Clock);
										@(posedge Clock);
										@(posedge Clock);
		begin_Evacuation <= 1;			@(posedge Clock);
										@(posedge Clock);
										@(posedge Clock);
										@(posedge Clock);
		OuterClosed <= 1;				@(posedge Clock);
		Evacuated <= 1;					@(posedge Clock);
										@(posedge Clock);
										@(posedge Clock);
										@(posedge Clock);
		begin_Evacuation <= 1;			@(posedge Clock);	
										@(posedge Clock);
										@(posedge Clock);
										@(posedge Clock);

	end
endmodule

Evacuate_testbench.v
`include "Evacuate.v"
`include "Evacuate_tester.v"

module Evacuate_testbench();

	wire Clock, Reset, InnerClosed, begin_Evacuation, OuterClosed, Evacuated;
	wire Evacuation;
	
	// Calls the 1 bit counter tester module 
	// Notice that the output Clock, Reset, Increase of the tester module are wires Clock, Reset, Increase in this module
	Evacuate_tester t(.Clock(Clock), .Reset(Reset), .begin_Evacuation(begin_Evacuation), .InnerClosed(InnerClosed), .OuterClosed(OuterClosed), .Evacuated(Evacuated));
	
	// Calls the 1 bit counter module as the device under test (dut)
	// Notice that the Clock, Reset, and Increase are wired to the input of the 1 bit counter module  
	Evacuate dut(.Clock(Clock), .Reset(Reset), .begin_Evacuation(begin_Evacuation), .InnerClosed(InnerClosed), .OuterClosed(OuterClosed), .Evacuated(Evacuated), .Evacuation(Evacuation));
	
	// Dumps the results of the simulation into a .vcd file for view in GTKWave
	initial begin 
		$dumpfile("Evacuate.vcd");
		$dumpvars(0, Evacuate_testbench);
		#150;
		$finish;
	end 
	
endmodule

Evacuate.vcd
$date
	Fri Apr 15 21:48:22 2016
$end
$version
	Icarus Verilog
$end
$timescale
	1s
$end
$scope module Evacuate_testbench $end
$var wire 1 ! Clock $end
$var wire 1 " Evacuated $end
$var wire 1 # Evacuation $end
$var wire 1 $ InnerClosed $end
$var wire 1 % OuterClosed $end
$var wire 1 & Reset $end
$var wire 1 ' begin_Evacuation $end
$scope module t $end
$var reg 1 ( Clock $end
$var reg 1 ) Evacuated $end
$var reg 1 * InnerClosed $end
$var reg 1 + OuterClosed $end
$var reg 1 , Reset $end
$var reg 1 - begin_Evacuation $end
$upscope $end
$scope module dut $end
$var wire 1 ! Clock $end
$var wire 1 " Evacuated $end
$var wire 1 # Evacuation $end
$var wire 1 $ InnerClosed $end
$var wire 1 % OuterClosed $end
$var wire 1 & Reset $end
$var wire 1 ' begin_Evacuation $end
$var reg 1 . ns $end
$var reg 1 / ps $end
$upscope $end
$upscope $end
$enddefinitions $end
#0
$dumpvars
x/
x.
x-
x,
x+
x*
x)
1(
x'
x&
x%
x$
x#
x"
1!
$end
#1
0(
0!
#2
1,
1&
1(
1!
#3
0(
0!
#4
0/
0#
1(
1!
#5
0(
0!
#6
0+
0%
0,
0&
1(
1!
#7
0(
0!
#8
0.
x/
x#
0*
0$
1(
1!
#9
0(
0!
#10
0)
0"
0/
0#
1(
1!
#11
0(
0!
#12
1(
1!
#13
0(
0!
#14
1-
1'
1(
1!
#15
0(
0!
#16
1(
1!
#17
0(
0!
#18
1(
1!
#19
0(
0!
#20
1(
1!
#21
0(
0!
#22
1)
1"
1(
1!
#23
0(
0!
#24
1(
1!
#25
0(
0!
#26
1(
1!
#27
0(
0!
#28
1(
1!
#29
0(
0!
#30
1(
1!
#31
0(
0!
#32
1(
1!
#33
0(
0!
#34
1*
1$
1(
1!
#35
0(
0!
#36
1(
1!
#37
0(
0!
#38
1(
1!
#39
0(
0!
#40
1+
1%
1(
1!
#41
0(
0!
#42
1.
0)
0"
1(
1!
#43
0(
0!
#44
1/
1#
1(
1!
#45
0(
0!
#46
1(
1!
#47
0(
0!
#48
1(
1!
#49
0(
0!
#50
1(
1!
#51
0(
0!
#52
1(
1!
#53
0(
0!
#54
1(
1!
#55
0(
0!
#56
1(
1!
#57
0(
0!
#58
0.
1)
1"
1(
1!
#59
0(
0!
#60
0/
0#
1(
1!
