EVState.v
module EVState (Clock, Reset, Increase, Count);
	input Clock, Reset, Increase;

	// Output scoreKeeper is 3 bit number that should send to displayVictor module
	output Count;
	
	// Your code goes here!!
	reg ps; // Present State
	reg ns; // Next State
	
	initial ps = 1;
	
	// Next State logic
	always @(*) begin
	
		case (Increase)
		
			1: begin
							
				ns = ps + 1; // case for when counter should go up by 1	

			end 
				
			0: begin
				
				ns = ps;
						
			end

		endcase
		
	end

	// Output logic - could also be another always, or part of above block.
	assign Count = (ps);
	
	// DFFs
	always @(posedge Clock)
		if (!Reset) begin
			ps <= 1;
		end 	
		else begin
			ps <= ns;
		end
endmodule

EVState_tester.v
module EVState_tester(Clock, Reset, Increase);
	output reg Clock, Reset, Increase;
	
	// Set up the clock.
	parameter CLOCK_PERIOD=2;
	initial Clock=1;
	always begin
		#(CLOCK_PERIOD/2);
		Clock = ~Clock;
	end
	
	// Set up the inputs to the design. Each line is a clock cycle.
	initial begin
										@(posedge Clock);
		Reset <= 0;						@(posedge Clock);			
										@(posedge Clock);
		Reset <= 1; Increase <= 1;		@(posedge Clock);
		Increase <= 0;					@(posedge Clock);
										@(posedge Clock);
		Increase <= 1;					@(posedge Clock);
		Increase <= 0;					@(posedge Clock);
										@(posedge Clock);
		Increase <= 1;					@(posedge Clock);
		Increase <= 0;					@(posedge Clock);
										@(posedge Clock);
		Increase <= 1;					@(posedge Clock);
		Increase <= 0;					@(posedge Clock);
										@(posedge Clock);
		Increase <= 1;					@(posedge Clock);
		Increase <= 0;					@(posedge Clock);
										@(posedge Clock);	

	end
endmodule

EVState_testbench.v
`include "EVState.v"
`include "EVState_tester.v"

module EVState_testbench();

	wire Clock, Reset, Increase;
	wire Count;
	
	// Calls the 1 bit counter tester module 
	// Notice that the output Clock, Reset, Increase of the tester module are wires Clock, Reset, Increase in this module
	EVState_tester t(.Clock(Clock), .Reset(Reset), .Increase(Increase));
	
	// Calls the 1 bit counter module as the device under test (dut)
	// Notice that the Clock, Reset, and Increase are wired to the input of the 1 bit counter module  
	EVState dut(.Clock(Clock), .Reset(Reset), .Increase(Increase), .Count(Count));
	
	// Dumps the results of the simulation into a .vcd file for view in GTKWave
	initial begin 
		$dumpfile("EVState.vcd");
		$dumpvars(0, EVState_testbench);
		#150;
		$finish;
	end 
	
endmodule

EVState.vcd
$date
	Thu Apr 21 10:35:44 2016
$end
$version
	Icarus Verilog
$end
$timescale
	1s
$end
$scope module EVState_testbench $end
$var wire 1 ! Clock $end
$var wire 1 " Count $end
$var wire 1 # Increase $end
$var wire 1 $ Reset $end
$scope module t $end
$var reg 1 % Clock $end
$var reg 1 & Increase $end
$var reg 1 ' Reset $end
$upscope $end
$scope module dut $end
$var wire 1 ! Clock $end
$var wire 1 " Count $end
$var wire 1 # Increase $end
$var wire 1 $ Reset $end
$var reg 1 ( ns $end
$var reg 1 ) ps $end
$upscope $end
$upscope $end
$enddefinitions $end
#0
$dumpvars
1)
x(
x'
x&
1%
x$
x#
1"
1!
$end
#1
0%
0!
#2
0'
0$
x)
x"
1%
1!
#3
0%
0!
#4
1)
1"
1%
1!
#5
0%
0!
#6
0(
1&
1#
1'
1$
1%
1!
#7
0%
0!
#8
0)
0"
0&
0#
1%
1!
#9
0%
0!
#10
1%
1!
#11
0%
0!
#12
1(
1&
1#
1%
1!
#13
0%
0!
#14
0&
0#
1)
1"
1%
1!
#15
0%
0!
#16
1%
1!
#17
0%
0!
#18
0(
1&
1#
1%
1!
#19
0%
0!
#20
0)
0"
0&
0#
1%
1!
#21
0%
0!
#22
1%
1!
#23
0%
0!
#24
1(
1&
1#
1%
1!
#25
0%
0!
#26
0&
0#
1)
1"
1%
1!
#27
0%
0!
#28
1%
1!
#29
0%
0!
#30
0(
1&
1#
1%
1!
#31
0%
0!
#32
0)
0"
0&
0#
1%
1!
