FillandPressurize.v
module FillandPressurize(Clock, Reset, begin_FandP, InnerClosed, OuterClosed, Pressurized, FandP);
	input Clock, Reset, begin_FandP, InnerClosed, OuterClosed, Pressurized;
	output FandP;
	
	parameter A = 0, B = 1;
	
	reg ps;
	reg ns;
	
	always@(*)
	
		case (OuterClosed)
		
			A: begin 
			
				ns = A;
			
			end 
			
			
			B: begin 
			
				if (!Pressurized && begin_FandP && InnerClosed) ns = B;
				else ns = A;
				
			end 
		
		endcase
		
	assign FandP = (ps); 
		
	always@(posedge Clock)
		if(!Reset) begin
		
			ps <= A;
			
		end 
				
		else begin
		
			ps <= ns;
			
		end 
	
endmodule

FillandPressurize_tester.v
module FillandPressurize_tester(Clock, Reset, begin_FandP, InnerClosed, OuterClosed, Pressurized);
	output reg Clock, Reset, begin_FandP, InnerClosed, OuterClosed, Pressurized;
	
	// Set up the clock.
	parameter CLOCK_PERIOD=2;
	initial Clock=1;
	always begin
		#(CLOCK_PERIOD/2);
		Clock = ~Clock;
	end
	
	// Set up the inputs to the design. Each line is a clock cycle.
	initial begin
										@(posedge Clock);
		Reset <= 1;						@(posedge Clock);			
										@(posedge Clock);
		Reset <= 0; OuterClosed <= 0;	@(posedge Clock);
		InnerClosed <= 0;				@(posedge Clock);
		Pressurized <= 0;				@(posedge Clock);
										@(posedge Clock);
		begin_FandP	<= 1;				@(posedge Clock);
										@(posedge Clock);
										@(posedge Clock);
										@(posedge Clock);
		Pressurized <= 1;				@(posedge Clock);
										@(posedge Clock);
										@(posedge Clock);
										@(posedge Clock);
		begin_FandP	<= 1;				@(posedge Clock);
										@(posedge Clock);
		InnerClosed <= 1;				@(posedge Clock);
										@(posedge Clock);
										@(posedge Clock);
		OuterClosed <= 1;				@(posedge Clock);
		Pressurized <= 0;				@(posedge Clock);
										@(posedge Clock);
										@(posedge Clock);
		begin_FandP	<= 1;				@(posedge Clock);
										@(posedge Clock);
										@(posedge Clock);
										@(posedge Clock);
		OuterClosed <= 1;				@(posedge Clock);
		Pressurized <= 1;				@(posedge Clock);
										@(posedge Clock);
										@(posedge Clock);
										@(posedge Clock);
		begin_FandP <= 1;				@(posedge Clock);	
										@(posedge Clock);
										@(posedge Clock);
										@(posedge Clock);

	end
endmodule

FillandPressurize_testbench.v
`include "FillandPressurize.v"
`include "FillandPressurize_tester.v"

module FillandPressurize_testbench();

	wire Clock, Reset, InnerClosed, begin_FandP, OuterClosed, Pressurized;
	wire FandP;
	
	// Calls the 1 bit counter tester module 
	// Notice that the output Clock, Reset, Increase of the tester module are wires Clock, Reset, Increase in this module
	FillandPressurize_tester t(.Clock(Clock), .Reset(Reset), .begin_FandP(begin_FandP), .InnerClosed(InnerClosed), .OuterClosed(OuterClosed), .Pressurized(Pressurized));
	
	// Calls the 1 bit counter module as the device under test (dut)
	// Notice that the Clock, Reset, and Increase are wired to the input of the 1 bit counter module  
	FillandPressurize dut(.Clock(Clock), .Reset(Reset), .begin_FandP(begin_FandP), .InnerClosed(InnerClosed), .OuterClosed(OuterClosed), .Pressurized(Pressurized), .FandP(FandP));
	
	// Dumps the results of the simulation into a .vcd file for view in GTKWave
	initial begin 
		$dumpfile("FillandPressurize.vcd");
		$dumpvars(0, FillandPressurize_testbench);
		#150;
		$finish;
	end 
	
endmodule

FillandPressurize.vcd
$date
	Sat Apr 16 19:15:35 2016
$end
$version
	Icarus Verilog
$end
$timescale
	1s
$end
$scope module FillandPressurize_testbench $end
$var wire 1 ! Clock $end
$var wire 1 " FandP $end
$var wire 1 # InnerClosed $end
$var wire 1 $ OuterClosed $end
$var wire 1 % Pressurized $end
$var wire 1 & Reset $end
$var wire 1 ' begin_FandP $end
$scope module t $end
$var reg 1 ( Clock $end
$var reg 1 ) InnerClosed $end
$var reg 1 * OuterClosed $end
$var reg 1 + Pressurized $end
$var reg 1 , Reset $end
$var reg 1 - begin_FandP $end
$upscope $end
$scope module dut $end
$var wire 1 ! Clock $end
$var wire 1 " FandP $end
$var wire 1 # InnerClosed $end
$var wire 1 $ OuterClosed $end
$var wire 1 % Pressurized $end
$var wire 1 & Reset $end
$var wire 1 ' begin_FandP $end
$var reg 1 . ns $end
$var reg 1 / ps $end
$upscope $end
$upscope $end
$enddefinitions $end
#0
$dumpvars
x/
x.
x-
x,
x+
x*
x)
1(
x'
x&
x%
x$
x#
x"
1!
$end
#1
0(
0!
#2
1,
1&
1(
1!
#3
0(
0!
#4
0/
0"
1(
1!
#5
0(
0!
#6
0.
0*
0$
0,
0&
1(
1!
#7
0(
0!
#8
0)
0#
1(
1!
#9
0(
0!
#10
0+
0%
1(
1!
#11
0(
0!
#12
1(
1!
#13
0(
0!
#14
1-
1'
1(
1!
#15
0(
0!
#16
1(
1!
#17
0(
0!
#18
1(
1!
#19
0(
0!
#20
1(
1!
#21
0(
0!
#22
1+
1%
1(
1!
#23
0(
0!
#24
1(
1!
#25
0(
0!
#26
1(
1!
#27
0(
0!
#28
1(
1!
#29
0(
0!
#30
1(
1!
#31
0(
0!
#32
1(
1!
#33
0(
0!
#34
1)
1#
1(
1!
#35
0(
0!
#36
1(
1!
#37
0(
0!
#38
1(
1!
#39
0(
0!
#40
1*
1$
1(
1!
#41
0(
0!
#42
1.
0+
0%
1(
1!
#43
0(
0!
#44
1/
1"
1(
1!
#45
0(
0!
#46
1(
1!
#47
0(
0!
#48
1(
1!
#49
0(
0!
#50
1(
1!
#51
0(
0!
#52
1(
1!
#53
0(
0!
#54
1(
1!
#55
0(
0!
#56
1(
1!
#57
0(
0!
#58
0.
1+
1%
1(
1!
#59
0(
0!
#60
0/
0"
1(
1!
