MetastabilityDFlipFlop.v
module MetastabilityDFlipFlop(q, qBar, D, clk);
	input D, clk;
	output q, qBar;
	reg q;
	not n1 (qBar, q);
		always@ (posedge clk)
		begin
			q <= D;
		end
endmodule

Metastability.v
// `include "MetastabilityDFlipFlop.v"

module Metastability ( clk, press, metaFree);
	input clk, press;
	output metaFree;
	
	wire d1_Out;
	
	// Fixes Metastability by putting signal through two D flip-flops 
	MetastabilityDFlipFlop d1(.q(d1_Out), .qBar(), .D(press), .clk(clk));
	MetastabilityDFlipFlop d2(.q(metaFree), .qBar(), .D(d1_Out), .clk(clk));
	
endmodule

Metastability_tester.v
// This module will drive the inputs reset and clock to the 4 bit ripple down 
// counter module for simulation in GTKWave
module Metastability_tester(rst, clk, in);

	output reg rst, clk, in;
	
	// Establishes clock for simulation of  4 bit ripple down counter 
	parameter clk_PERIOD=2;
	initial clk=1;
	always begin
		#(clk_PERIOD/2);
		clk = ~clk;
	end 

	// Establishes reset for simulation of the making the user input high for once clock cycle
	initial begin
												@(posedge clk);
		rst <= 1; in <= 1;						@(posedge clk);
												@(posedge clk);
												@(posedge clk);
												@(posedge clk);
		in <= 0;								@(posedge clk);
												@(posedge clk);
												@(posedge clk);
		in <= 1;								@(posedge clk);
												@(posedge clk);
												@(posedge clk);
		in <= 0;								@(posedge clk);
		in <= 1;								@(posedge clk);
		in <= 0;								@(posedge clk);
												@(posedge clk);
	end
	
endmodule

Metastability_testbench.v
`include "Metastability_tester.v"
`include "Metastability.v"

// This module is the testbench that will save the results of the simulation for viewing in GTKWave 
module Metastability_testbench();
	wire clk, rst, in;
	wire out;
	
	// Calls the 4 bit ripple down counter tester module 
	// Notice that the output clock and reset of the tester module are wires clk and rst in this module
	Metastability_tester t(.clk(clk), .in(in));
	
	// Calls the metastability module
	Metastability dut( .clk(clk), .press(in), .metaFree(out));
	
	// Dumps the results of the simulation into a .vcd file for view in GTKWave
	initial begin 
		$dumpfile("Metastability.vcd");
		$dumpvars(0, Metastability_testbench);
		#150;
		$finish;
	end 

endmodule

Metastability.vcd
$date
	Sat Apr 23 08:59:25 2016
$end
$version
	Icarus Verilog
$end
$timescale
	1s
$end
$scope module Metastability_testbench $end
$var wire 1 ! clk $end
$var wire 1 " in $end
$var wire 1 # out $end
$scope module t $end
$var reg 1 $ clk $end
$var reg 1 % in $end
$var reg 1 & rst $end
$upscope $end
$scope module dut $end
$var wire 1 ! clk $end
$var wire 1 ' d1_Out $end
$var wire 1 # metaFree $end
$var wire 1 " press $end
$scope module d1 $end
$var wire 1 " D $end
$var wire 1 ! clk $end
$var wire 1 ( qBar $end
$var reg 1 ) q $end
$upscope $end
$scope module d2 $end
$var wire 1 ' D $end
$var wire 1 ! clk $end
$var wire 1 * qBar $end
$var reg 1 + q $end
$upscope $end
$upscope $end
$upscope $end
$enddefinitions $end
#0
$dumpvars
x+
x*
x)
x(
x'
1&
x%
1$
x#
x"
1!
$end
#1
0$
0!
#2
0&
1$
1!
#3
0$
0!
#4
1$
1!
#5
0$
0!
#6
1$
1!
#7
0$
0!
#8
1%
1"
1&
1$
1!
#9
0$
0!
#10
0(
1)
1'
1$
1!
#11
0$
0!
#12
0*
1+
1#
1$
1!
#13
0$
0!
#14
1$
1!
#15
0$
0!
#16
0%
0"
1$
1!
#17
0$
0!
#18
1(
0)
0'
1$
1!
#19
0$
0!
#20
1*
0+
0#
1$
1!
#21
0$
0!
#22
1%
1"
1$
1!
#23
0$
0!
#24
0(
1)
1'
1$
1!
#25
0$
0!
#26
0*
1+
1#
1$
1!
#27
0$
0!
#28
1$
1!
#29
0$
0!
#30
0&
1$
1!
#31
0$
0!
#32
1$
1!
#33
0$
0!
#34
1$
1!
#35
0$
0!
#36
0%
0"
1$
1!
#37
0$
0!
#38
1(
1%
1"
0)
0'
1$
1!
#39
0$
0!
#40
1*
0(
0+
0#
1)
1'
0%
0"
1$
1!
#41
0$
0!
#42
1(
0*
0)
0'
1+
1#
1$
1!
#43
0$
0!
#44
1*
0+
0#
1$
1!
