UserInput_High2Low.v
module UserInput_High2Low (Clock, Reset, in, out);
	input Clock, Reset, in;
	output out;
	
	// Your code goes here!!
	reg ps; // Present State
	reg ns; // Next State

	// State encoding.
	parameter A = 0, B = 1;
	
	// Next State logic
	always @(*)
		case (in)
			A: if (ps == 0) ns <= 1; // case for when KEY is unpressed and becomes pressed. 
				else if (ps == 1) ns <= 1;
			B: if (ps == 0) ns <= 0;
				else if (ps == 1) ns <= 0;
			
			default: ns = 1'bx;
		endcase
		
	// Output logic - could also be another always, or part of above block.
	assign out = (~ps & ns);
	
	// DFFs
	always @(posedge Clock)
		if (Reset)
			ps <= B;
		else
			ps <= ns;
endmodule

/*
module userInput_FSM_testbench();
	reg Clock, Reset, in;
	wire out, ps, ns;
	
	userInput_FSM dut (Clock, Reset, in, out);
	
	// Set up the clock.
	parameter CLOCK_PERIOD=100;
	initial Clock=1;
	always begin
		#(CLOCK_PERIOD/2);
		Clock = ~Clock;
	end
	
	// Set up the inputs to the design. Each line is a clock cycle.
	initial begin
												@(posedge Clock);
		Reset <= 1; in <= 1;				@(posedge Clock);
												@(posedge Clock);
		Reset <= 0; 			 			@(posedge Clock);
												@(posedge Clock);
		in <= 0;								@(posedge Clock);
												@(posedge Clock);
												@(posedge Clock);
		in <= 1;								@(posedge Clock);
												@(posedge Clock);
												@(posedge Clock);
		in <= 0;								@(posedge Clock);
		in <= 1;								@(posedge Clock);
		in <= 0;								@(posedge Clock);
												@(posedge Clock);
		$stop; // End the simulation.
	end
endmodule
*/

UserInput_High2Low_tester.v
// This module will drive the inputs reset and clock to the 4 bit ripple down 
// counter module for simulation in GTKWave
module UserInput_High2Low_tester(rst, clk, in);

	output reg rst, clk, in;
	
	// Establishes clock for simulation of  4 bit ripple down counter 
	parameter clk_PERIOD=2;
	initial clk=1;
	always begin
		#(clk_PERIOD/2);
		clk = ~clk;
	end 

	// Establishes reset for simulation of the making the user input high for once clock cycle
	initial begin
												@(posedge clk);
		rst <= 0; in <= 1;					@(posedge clk);
												@(posedge clk);
		rst<= 1; 			 				@(posedge clk);
												@(posedge clk);
		in <= 0;								@(posedge clk);
												@(posedge clk);
												@(posedge clk);
		in <= 1;								@(posedge clk);
												@(posedge clk);
												@(posedge clk);
		in <= 0;								@(posedge clk);
		in <= 1;								@(posedge clk);
		in <= 0;								@(posedge clk);
												@(posedge clk);
	end
	
endmodule

UserInput_High2Low_testbench.v
`include "UserInput_High2Low_tester.v"
`include "UserInput_High2Low.v"

// This module is the testbench that will save the results of the simulation for viewing in GTKWave 
module UserInput_High2Low_testbench();
	wire clk, rst, in;
	wire out;
	
	// Calls the 4 bit ripple down counter tester module 
	// Notice that the output clock and reset of the tester module are wires clk and rst in this module
	UserInput_High2Low_tester t(.clk(clk), .rst(rst), .in(in));
	
	// Calls the RippleDownCounter_4bit module as the device under test (dut)
	// Notice that the clock and reset wire are wired to the input clk and rst of the 4 bit ripple down counter module  
	UserInput_High2Low dut(.Clock(clk), .Reset(rst), .in(in), .out(out));
	
	// Dumps the results of the simulation into a .vcd file for view in GTKWave
	initial begin 
		$dumpfile("UserInput_High2Low.vcd");
		$dumpvars(0, UserInput_High2Low_testbench);
		#150;
		$finish;
	end 

endmodule

UserInput_High2Low.vcd
$date
	Wed Apr 20 09:14:03 2016
$end
$version
	Icarus Verilog
$end
$timescale
	1s
$end
$scope module UserInput_High2Low_testbench $end
$var wire 1 ! clk $end
$var wire 1 " in $end
$var wire 1 # out $end
$var wire 1 $ rst $end
$scope module t $end
$var reg 1 % clk $end
$var reg 1 & in $end
$var reg 1 ' rst $end
$upscope $end
$scope module dut $end
$var wire 1 ! Clock $end
$var wire 1 $ Reset $end
$var wire 1 " in $end
$var wire 1 # out $end
$var reg 1 ( ns $end
$var reg 1 ) ps $end
$upscope $end
$upscope $end
$enddefinitions $end
#0
$dumpvars
x)
x(
x'
x&
1%
x$
x#
x"
1!
$end
#1
0%
0!
#2
1&
1"
0'
0$
1%
1!
#3
0%
0!
#4
0(
0#
1)
1%
1!
#5
0%
0!
#6
1'
1$
1%
1!
#7
0%
0!
#8
0)
1%
1!
#9
0%
0!
#10
1#
1(
0&
0"
1%
1!
#11
0%
0!
#12
0#
1)
1%
1!
#13
0%
0!
#14
1%
1!
#15
0%
0!
#16
0(
1&
1"
1%
1!
#17
0%
0!
#18
0)
1%
1!
#19
0%
0!
#20
1%
1!
#21
0%
0!
#22
1#
1(
0&
0"
1%
1!
#23
0%
0!
#24
0(
0#
1)
1&
1"
1%
1!
#25
0%
0!
#26
1#
1(
0&
0"
0)
1%
1!
#27
0%
0!
#28
0#
1)
1%
1!
